globantapi/__init__.py
globantapi/_decorators.py
globantapi/_exceptions.py
globantapi/_proxy.py
globantapi/apiClient.py
globantapi/controller.py
globantapi/eventSource.py
globantapi/repository.py
globantapi/typedef.py
globantapi/utils.py
globantapi-0.0.7.dist-info/METADATA
globantapi-0.0.7.dist-info/WHEEL
globantapi-0.0.7.dist-info/RECORD
